{
    "MyBehavior": {
        "checkpoints": [
            {
                "steps": 30599949,
                "file_path": "results\\BossPart1Try7\\MyBehavior\\MyBehavior-30599949.onnx",
                "reward": -6.39036884986692,
                "creation_time": 1750806566.7882912,
                "auxillary_file_paths": [
                    "results\\BossPart1Try7\\MyBehavior\\MyBehavior-30599949.pt"
                ]
            },
            {
                "steps": 30899949,
                "file_path": "results\\BossPart1Try7\\MyBehavior\\MyBehavior-30899949.onnx",
                "reward": -5.883765434473753,
                "creation_time": 1750813629.7220242,
                "auxillary_file_paths": [
                    "results\\BossPart1Try7\\MyBehavior\\MyBehavior-30899949.pt"
                ]
            },
            {
                "steps": 31199958,
                "file_path": "results\\BossPart1Try7\\MyBehavior\\MyBehavior-31199958.onnx",
                "reward": -5.665109833081563,
                "creation_time": 1750820623.6365054,
                "auxillary_file_paths": [
                    "results\\BossPart1Try7\\MyBehavior\\MyBehavior-31199958.pt"
                ]
            },
            {
                "steps": 31499974,
                "file_path": "results\\BossPart1Try7\\MyBehavior\\MyBehavior-31499974.onnx",
                "reward": -3.362887416034937,
                "creation_time": 1750827626.7811277,
                "auxillary_file_paths": [
                    "results\\BossPart1Try7\\MyBehavior\\MyBehavior-31499974.pt"
                ]
            },
            {
                "steps": 31678442,
                "file_path": "results\\BossPart1Try7\\MyBehavior\\MyBehavior-31678442.onnx",
                "reward": -5.164046271571091,
                "creation_time": 1750831857.369045,
                "auxillary_file_paths": [
                    "results\\BossPart1Try7\\MyBehavior\\MyBehavior-31678442.pt"
                ]
            }
        ],
        "final_checkpoint": {
            "steps": 31678442,
            "file_path": "results\\BossPart1Try7\\MyBehavior.onnx",
            "reward": -5.164046271571091,
            "creation_time": 1750831857.369045,
            "auxillary_file_paths": [
                "results\\BossPart1Try7\\MyBehavior\\MyBehavior-31678442.pt"
            ]
        }
    },
    "metadata": {
        "stats_format_version": "0.3.0",
        "mlagents_version": "0.26.0",
        "torch_version": "2.7.0+cu118"
    }
}